MANIFEST.in
README.rst
setup.py
c/gaepsi.h
c/kernel.c
c/octtree.c
c/quadcurve.c
c/sphrasterize.c
c/svremap.c
c/transform.c
gaepsi2/__init__.py
gaepsi2/_painter.c
gaepsi2/_painter.pyx
gaepsi2/camera.py
gaepsi2/color.py
gaepsi2/cosmology.py
gaepsi2/painter.py
gaepsi2/svr.c
gaepsi2/svr.pyx
gaepsi2/version.py
gaepsi2.egg-info/PKG-INFO
gaepsi2.egg-info/SOURCES.txt
gaepsi2.egg-info/dependency_links.txt
gaepsi2.egg-info/not-zip-safe
gaepsi2.egg-info/requires.txt
gaepsi2.egg-info/top_level.txt
gaepsi2/tests/__init__.py
gaepsi2/tests/test_all.py