Metadata-Version: 1.0
Name: gaepsi2
Version: 0.1.2
Summary: gaepsi2. SPH visualization.
Home-page: http://github.com/rainwoodman/gaepsi2
Author: Yu Feng
Author-email: rainwoodman@gmail.com
License: BSD-2-Clause
Platform: UNKNOWN
